a3grpc/__init__.py
a3grpc/patcher.py
a3grpc/type_hints.py
a3grpc/client/__init__.py
a3grpc/client/base_client.py
a3grpc/server/__init__.py
a3grpc/server/start.py
a3grpc/server/views/__init__.py
a3grpc/server/views/stream_to_stream_view.py
a3grpc/server/views/stream_to_unary_view.py
a3grpc/server/views/unary_to_stream_view.py
a3grpc/server/views/unary_to_unary_view.py
a3grpc/server/views/view_utils.py
a3grpc-0.3.0.dist-info/LICENSE
a3grpc-0.3.0.dist-info/METADATA
a3grpc-0.3.0.dist-info/WHEEL
a3grpc-0.3.0.dist-info/top_level.txt
a3grpc-0.3.0.dist-info/RECORD
